odoo/addons/scrap_reason_code/README.rst
odoo/addons/scrap_reason_code/__init__.py
odoo/addons/scrap_reason_code/__manifest__.py
odoo/addons/scrap_reason_code/i18n/scrap_reason_code.pot
odoo/addons/scrap_reason_code/migrations/13.0.1.1.0/pre-migration.py
odoo/addons/scrap_reason_code/models/__init__.py
odoo/addons/scrap_reason_code/models/reason_code.py
odoo/addons/scrap_reason_code/models/stock_move.py
odoo/addons/scrap_reason_code/models/stock_scrap.py
odoo/addons/scrap_reason_code/readme/CONFIGURE.rst
odoo/addons/scrap_reason_code/readme/CONTRIBUTORS.rst
odoo/addons/scrap_reason_code/readme/CREDITS.rst
odoo/addons/scrap_reason_code/readme/DESCRIPTION.rst
odoo/addons/scrap_reason_code/readme/ROADMAP.rst
odoo/addons/scrap_reason_code/readme/USAGE.rst
odoo/addons/scrap_reason_code/security/ir.model.access.csv
odoo/addons/scrap_reason_code/static/description/icon.png
odoo/addons/scrap_reason_code/static/description/index.html
odoo/addons/scrap_reason_code/tests/__init__.py
odoo/addons/scrap_reason_code/tests/test_scrap_reason_code.py
odoo/addons/scrap_reason_code/views/reason_code_view.xml
odoo/addons/scrap_reason_code/views/stock_move_views.xml
odoo/addons/scrap_reason_code/views/stock_scrap_views.xml
odoo13_addon_scrap_reason_code-13.0.1.1.1.dist-info/METADATA
odoo13_addon_scrap_reason_code-13.0.1.1.1.dist-info/WHEEL
odoo13_addon_scrap_reason_code-13.0.1.1.1.dist-info/top_level.txt
odoo13_addon_scrap_reason_code-13.0.1.1.1.dist-info/RECORD
